docmesh_agent/__init__.py
docmesh_agent/agent.py
docmesh_agent/loader.py
docmesh_agent/utils.py
docmesh_agent/embeddings/__init__.py
docmesh_agent/embeddings/embeddings.py
docmesh_agent/memory/__init__.py
docmesh_agent/memory/memory.py
docmesh_agent/parser/__init__.py
docmesh_agent/parser/output_parser.py
docmesh_agent/toolkit/__init__.py
docmesh_agent/toolkit/common.py
docmesh_agent/toolkit/cypher.py
docmesh_agent/toolkit/entity.py
docmesh_agent/toolkit/paper.py
docmesh_agent/toolkit/recommend.py
docmesh_agent/tools/__init__.py
docmesh_agent/tools/base.py
docmesh_agent/tools/common.py
docmesh_agent/tools/cypher.py
docmesh_agent/tools/entity.py
docmesh_agent/tools/paper.py
docmesh_agent/tools/recommend.py
docmesh_agent/tools/template.py
docmesh_agent-0.0.20.dist-info/WHEEL
docmesh_agent-0.0.20.dist-info/METADATA
docmesh_agent-0.0.20.dist-info/RECORD
