Metadata-Version: 2.3
Name: docmesh_agent
Version: 0.0.20
Summary: Agent helps you dig the paper connection!
Author-email: Zhengkai Yang <kyle.yang1995@gmail.com>
Requires-Python: >=3.8
Classifier: Programming Language :: Python :: 3.8
Classifier: Programming Language :: Python :: 3.9
Classifier: Programming Language :: Python :: 3.10
Classifier: Operating System :: OS Independent
Requires-Dist: docmesh-core>=0.0.18
Requires-Dist: colorama>=0.4.6
Requires-Dist: pymupdf>=1.24.3
Requires-Dist: faiss-cpu>=1.8.0
Requires-Dist: langchain>=0.1.15
Requires-Dist: langchain-openai>=0.1.3
Requires-Dist: langchain-community==0.2.2
Requires-Dist: langchainhub>=0.1.15
